{"_type":"export","__export_format":4,"__export_date":"2024-10-11T12:26:13.139Z","__export_source":"insomnia.desktop.app:v10.0.0","resources":[{"_id":"req_a6e053024e6d47b0b65a84a47559ec64","parentId":"fld_df0eccb16d7a40c6bf8abbc8003fa1bb","modified":1728582199380,"created":1728582178353,"url":"{{ _.base_url }}/purchaseOrder/allMaterialsB","name":"All Purchasing Orders Materials B","description":"","method":"GET","body":{},"parameters":[],"headers":[{"name":"User-Agent","value":"insomnia/10.0.0"}],"authentication":{},"metaSortKey":-1728582178353,"isPrivate":false,"pathParameters":[],"settingStoreCookies":true,"settingSendCookies":true,"settingDisableRenderRequestBody":false,"settingEncodeUrl":true,"settingRebuildPath":true,"settingFollowRedirects":"global","_type":"request"},{"_id":"fld_df0eccb16d7a40c6bf8abbc8003fa1bb","parentId":"wrk_scratchpad","modified":1728501684977,"created":1728501684977,"name":"Purchase Order","description":"","environment":{},"environmentPropertyOrder":null,"metaSortKey":-1728501684978,"_type":"request_group"},{"_id":"wrk_scratchpad","parentId":null,"modified":1719401699301,"created":1719401699301,"name":"Scratch Pad","description":"","scope":"collection","_type":"workspace"},{"_id":"req_7ef1e753a0ae4553b63e79ca1820df3e","parentId":"fld_df0eccb16d7a40c6bf8abbc8003fa1bb","modified":1728582166087,"created":1728561795403,"url":"{{ _.base_url }}/purchaseOrder/allMaterialsA","name":"All Purchasing Orders Materials A","description":"","method":"GET","body":{},"parameters":[],"headers":[{"name":"User-Agent","value":"insomnia/10.0.0"}],"authentication":{},"metaSortKey":-1728561795403,"isPrivate":false,"pathParameters":[],"settingStoreCookies":true,"settingSendCookies":true,"settingDisableRenderRequestBody":false,"settingEncodeUrl":true,"settingRebuildPath":true,"settingFollowRedirects":"global","_type":"request"},{"_id":"req_e3e2619e425a4a9c99c1f471f8dc3c31","parentId":"fld_df0eccb16d7a40c6bf8abbc8003fa1bb","modified":1728647839823,"created":1728512117725,"url":"{{ _.base_url }}/purchaseOrder/updatePurchasingOrder/2","name":"Update Purchasing Order","description":"","method":"PUT","body":{"mimeType":"application/json","text":"{\n\t\"demand\": \"60\",\n\t\"orderReceived\": \"2\" \n}\n"},"parameters":[],"headers":[{"name":"Content-Type","value":"application/json"},{"name":"User-Agent","value":"insomnia/10.0.0"}],"authentication":{},"metaSortKey":-1728512117725,"isPrivate":false,"pathParameters":[],"settingStoreCookies":true,"settingSendCookies":true,"settingDisableRenderRequestBody":false,"settingEncodeUrl":true,"settingRebuildPath":true,"settingFollowRedirects":"global","_type":"request"},{"_id":"req_f71e84ed4b2c45b89ff4b35d66fe61b2","parentId":"fld_df0eccb16d7a40c6bf8abbc8003fa1bb","modified":1728647787916,"created":1728501691412,"url":"{{ _.base_url }}/purchaseOrder/2","name":"First Week Purchase","description":"","method":"POST","body":{},"parameters":[],"headers":[{"name":"User-Agent","value":"insomnia/10.0.0"}],"authentication":{},"metaSortKey":-1728501691412,"isPrivate":false,"pathParameters":[],"settingStoreCookies":true,"settingSendCookies":true,"settingDisableRenderRequestBody":false,"settingEncodeUrl":true,"settingRebuildPath":true,"settingFollowRedirects":"global","_type":"request"},{"_id":"req_2db60c1f21494b799fe43dee4a827de1","parentId":"fld_db33e6838148418280030b68ab44596a","modified":1728647962077,"created":1728582209885,"url":"{{ _.base_url }}/inventory/all","name":"All Inventories","description":"","method":"GET","body":{},"parameters":[],"headers":[{"name":"User-Agent","value":"insomnia/10.0.0"}],"authentication":{},"metaSortKey":-1728582209885,"isPrivate":false,"pathParameters":[],"settingStoreCookies":true,"settingSendCookies":true,"settingDisableRenderRequestBody":false,"settingEncodeUrl":true,"settingRebuildPath":true,"settingFollowRedirects":"global","_type":"request"},{"_id":"fld_db33e6838148418280030b68ab44596a","parentId":"wrk_scratchpad","modified":1728478854045,"created":1728478854045,"name":"Inventory","description":"","environment":{},"environmentPropertyOrder":null,"metaSortKey":-1728478854045,"_type":"request_group"},{"_id":"req_6e09358c967141eea4a38d92a0519053","parentId":"fld_db33e6838148418280030b68ab44596a","modified":1728647769570,"created":1728478857904,"url":"{{ _.base_url }}/inventory/register/2","name":"First Week Inventory","description":"","method":"POST","body":{},"parameters":[],"headers":[{"name":"User-Agent","value":"insomnia/10.0.0"}],"authentication":{},"metaSortKey":-1728478857904,"isPrivate":false,"pathParameters":[],"settingStoreCookies":true,"settingSendCookies":true,"settingDisableRenderRequestBody":false,"settingEncodeUrl":true,"settingRebuildPath":true,"settingFollowRedirects":"global","_type":"request"},{"_id":"req_8a05c7e7333145cf94247d8587ba434d","parentId":"fld_e0069254fa714d35ae0b4587082052b5","modified":1728328747650,"created":1728328623312,"url":"{{ _.base_url }}/material/delete_registered_item_by_id/3","name":"Delete Material","description":"","method":"DELETE","body":{"mimeType":"application/json","text":""},"parameters":[],"headers":[{"name":"Content-Type","value":"application/json"},{"name":"User-Agent","value":"insomnia/10.0.0"}],"authentication":{},"metaSortKey":-1728328623312,"isPrivate":false,"pathParameters":[],"settingStoreCookies":true,"settingSendCookies":true,"settingDisableRenderRequestBody":false,"settingEncodeUrl":true,"settingRebuildPath":true,"settingFollowRedirects":"global","_type":"request"},{"_id":"fld_e0069254fa714d35ae0b4587082052b5","parentId":"wrk_scratchpad","modified":1727781835263,"created":1727781835263,"name":"Create a Material","description":"","environment":{},"environmentPropertyOrder":null,"metaSortKey":-1727781835263,"_type":"request_group"},{"_id":"req_0855091fe1ac40df9aa0aa8c16444ace","parentId":"fld_e0069254fa714d35ae0b4587082052b5","modified":1728512050957,"created":1727952040153,"url":"{{ _.base_url }}/material/2","name":"Get by Id","description":"","method":"GET","body":{},"parameters":[],"headers":[{"name":"User-Agent","value":"insomnia/10.0.0"}],"authentication":{},"metaSortKey":-1727952040153,"isPrivate":false,"pathParameters":[],"settingStoreCookies":true,"settingSendCookies":true,"settingDisableRenderRequestBody":false,"settingEncodeUrl":true,"settingRebuildPath":true,"settingFollowRedirects":"global","_type":"request"},{"_id":"req_04e17ab8304040e99b15bca0c4da6711","parentId":"fld_e0069254fa714d35ae0b4587082052b5","modified":1727966174673,"created":1727952028487,"url":"{{ _.base_url }}/material/materials","name":"Get all materials","description":"","method":"GET","body":{},"parameters":[],"headers":[{"name":"User-Agent","value":"insomnia/10.0.0"}],"authentication":{},"metaSortKey":-1727952028487,"isPrivate":false,"pathParameters":[],"settingStoreCookies":true,"settingSendCookies":true,"settingDisableRenderRequestBody":false,"settingEncodeUrl":true,"settingRebuildPath":true,"settingFollowRedirects":"global","_type":"request"},{"_id":"req_35c44fc29ede436ea83a0318912dfab3","parentId":"fld_e0069254fa714d35ae0b4587082052b5","modified":1728647754811,"created":1727781845819,"url":"{{ _.base_url }}/material","name":"Create Material","description":"","method":"POST","body":{"mimeType":"application/json","text":"{\n\t\"materialCode\": \"1240\",\n\t\"demand\": \"8\", \n\t\"inicialInventory\":\"20\",\n\t\"safetyStock\": \"10\"\n}\t"},"parameters":[],"headers":[{"name":"Content-Type","value":"application/json"},{"name":"User-Agent","value":"insomnia/10.0.0"}],"authentication":{},"metaSortKey":-1727781845819,"isPrivate":false,"pathParameters":[],"settingStoreCookies":true,"settingSendCookies":true,"settingDisableRenderRequestBody":false,"settingEncodeUrl":true,"settingRebuildPath":true,"settingFollowRedirects":"global","_type":"request"},{"_id":"req_5ee7eda8ebed40d78b467e87a286100e","parentId":"fld_2ed7dca4c1a44729bcf3a14a4c6e9b6c","modified":1728328895831,"created":1727952115223,"url":"{{ _.base_url }}/inforecord/1","name":"Get by Id","description":"","method":"GET","body":{},"parameters":[],"headers":[{"name":"User-Agent","value":"insomnia/10.0.0"}],"authentication":{},"metaSortKey":-1727952115223,"isPrivate":false,"pathParameters":[],"settingStoreCookies":true,"settingSendCookies":true,"settingDisableRenderRequestBody":false,"settingEncodeUrl":true,"settingRebuildPath":true,"settingFollowRedirects":"global","_type":"request"},{"_id":"fld_2ed7dca4c1a44729bcf3a14a4c6e9b6c","parentId":"wrk_scratchpad","modified":1727781825389,"created":1727781825389,"name":"Create a Info Record","description":"","environment":{},"environmentPropertyOrder":null,"metaSortKey":-1727781825389,"_type":"request_group"},{"_id":"req_2b362d9541c641c39be3fdcb1ba3b839","parentId":"fld_2ed7dca4c1a44729bcf3a14a4c6e9b6c","modified":1728328894875,"created":1727952095159,"url":"{{ _.base_url }}/inforecord/inforecord","name":"Get all inforecords","description":"","method":"GET","body":{},"parameters":[],"headers":[{"name":"User-Agent","value":"insomnia/10.0.0"}],"authentication":{},"metaSortKey":-1727869774972.5,"isPrivate":false,"pathParameters":[],"settingStoreCookies":true,"settingSendCookies":true,"settingDisableRenderRequestBody":false,"settingEncodeUrl":true,"settingRebuildPath":true,"settingFollowRedirects":"global","_type":"request"},{"_id":"req_6644e57fe0184f8582d9e28dd151cc37","parentId":"fld_2ed7dca4c1a44729bcf3a14a4c6e9b6c","modified":1728328841654,"created":1727787454786,"url":"{{ _.base_url }}/inforecord","name":"Create Info Record","description":"","method":"POST","body":{"mimeType":"application/json","text":"{\n\t\"price\": \"20.00\",\n\t\"leadTime\": \"1\"\n}"},"parameters":[],"headers":[{"name":"Content-Type","value":"application/json"},{"name":"User-Agent","value":"insomnia/10.0.0"}],"authentication":{},"metaSortKey":-1727787454786,"isPrivate":false,"pathParameters":[],"settingStoreCookies":true,"settingSendCookies":true,"settingDisableRenderRequestBody":false,"settingEncodeUrl":true,"settingRebuildPath":true,"settingFollowRedirects":"global","_type":"request"},{"_id":"env_99d30891da4bdcebc63947a8fc17f076de878684","parentId":"wrk_scratchpad","modified":1727791817239,"created":1720790236079,"name":"Base Environment","data":{"base_url":"http://localhost:8080"},"dataPropertyOrder":{"&":["base_url"]},"color":null,"isPrivate":false,"metaSortKey":1720790236079,"_type":"environment"},{"_id":"jar_99d30891da4bdcebc63947a8fc17f076de878684","parentId":"wrk_scratchpad","modified":1720790236094,"created":1720790236094,"name":"Default Jar","cookies":[],"_type":"cookie_jar"}]}